Metadata-Version: 1.0
Name: differentiate
Version: 1.1.9
Summary: Lightweight data differentiator.
Home-page: https://github.com/mrstephenneal/differentiate
Author: Stephen Neal
Author-email: stephen@stephenneal.net
License: MIT License
Platform: UNKNOWN
